lg/__init__.py
simply_just_logic_gates-3.dist-info/METADATA
simply_just_logic_gates-3.dist-info/WHEEL
simply_just_logic_gates-3.dist-info/top_level.txt
simply_just_logic_gates-3.dist-info/RECORD
