Metadata-Version: 2.4
Name: simply_just_logic_gates
Version: 3
Summary: Simply Just Logic Gates
Author: Error Dev
Author-email: 3rr0r.d3v@gmail.com
Classifier: Programming Language :: Python
Classifier: Environment :: Console
Classifier: Framework :: IDLE
Classifier: Natural Language :: English
Requires-Python: >=3.6
Dynamic: author
Dynamic: author-email
Dynamic: classifier
Dynamic: description
Dynamic: description-content-type
Dynamic: requires-python
Dynamic: summary
